rssreruns/__init__.py
rssreruns/elementwrapper.py
rssreruns/feedmodifier.py
rssreruns-0.0.15.dist-info/licenses/LICENSE.txt
rssreruns-0.0.15.dist-info/METADATA
rssreruns-0.0.15.dist-info/WHEEL
rssreruns-0.0.15.dist-info/top_level.txt
rssreruns-0.0.15.dist-info/RECORD
