Metadata-Version: 2.4
Name: rssreruns
Version: 0.0.15
Summary: Rebroadcast old RSS/Atom feed items to a new feed, in shuffled or chronological order.
Author-email: Hannah Connolly <hannah.d.connolly@gmail.com>
License: MIT License
Project-URL: Homepage, https://github.com/hannahlog/rss-reruns
Project-URL: Bug Tracker, https://github.com/hannahlog/rss-reruns/issues
Project-URL: Changelog, https://github.com/hannahlog/rss-reruns/blob/main/CHANGELOG.md
Classifier: Programming Language :: Python :: 3
Classifier: License :: OSI Approved :: MIT License
Classifier: Operating System :: OS Independent
Requires-Python: >=3.7
License-File: LICENSE.txt
Requires-Dist: certifi==2025.4.26
Requires-Dist: charset-normalizer==3.4.2
Requires-Dist: idna==3.10
Requires-Dist: lxml==5.4.0
Requires-Dist: python-dateutil==2.9.0.post0
Requires-Dist: requests==2.32.3
Requires-Dist: six==1.17.0
Requires-Dist: urllib3==2.4.0
Provides-Extra: dev
Requires-Dist: attrs==22.2.0; extra == "dev"
Requires-Dist: build==0.10.0; extra == "dev"
Requires-Dist: cachetools==5.3.0; extra == "dev"
Requires-Dist: certifi==2025.4.26; extra == "dev"
Requires-Dist: cfgv==3.3.1; extra == "dev"
Requires-Dist: chardet==5.1.0; extra == "dev"
Requires-Dist: charset-normalizer==3.4.2; extra == "dev"
Requires-Dist: click==8.1.3; extra == "dev"
Requires-Dist: colorama==0.4.6; extra == "dev"
Requires-Dist: distlib==0.3.6; extra == "dev"
Requires-Dist: filelock==3.9.0; extra == "dev"
Requires-Dist: identify==2.5.15; extra == "dev"
Requires-Dist: idna==3.10; extra == "dev"
Requires-Dist: iniconfig==2.0.0; extra == "dev"
Requires-Dist: lxml==5.4.0; extra == "dev"
Requires-Dist: lxml-stubs==0.4.0; extra == "dev"
Requires-Dist: mypy==0.991; extra == "dev"
Requires-Dist: mypy-extensions==0.4.3; extra == "dev"
Requires-Dist: nodeenv==1.7.0; extra == "dev"
Requires-Dist: packaging==23.0; extra == "dev"
Requires-Dist: pip-tools==6.12.1; extra == "dev"
Requires-Dist: platformdirs==2.6.2; extra == "dev"
Requires-Dist: pluggy==1.0.0; extra == "dev"
Requires-Dist: pre-commit==4.2.0; extra == "dev"
Requires-Dist: pyproject-api==1.5.0; extra == "dev"
Requires-Dist: pyproject-hooks==1.0.0; extra == "dev"
Requires-Dist: pytest==7.2.1; extra == "dev"
Requires-Dist: python-dateutil==2.9.0.post0; extra == "dev"
Requires-Dist: pyyaml==6.0.2; extra == "dev"
Requires-Dist: requests==2.32.3; extra == "dev"
Requires-Dist: six==1.17.0; extra == "dev"
Requires-Dist: tox==4.3.5; extra == "dev"
Requires-Dist: types-python-dateutil==2.8.19.6; extra == "dev"
Requires-Dist: types-requests==2.28.11.8; extra == "dev"
Requires-Dist: types-urllib3==1.26.25.4; extra == "dev"
Requires-Dist: typing-extensions==4.4.0; extra == "dev"
Requires-Dist: urllib3==2.4.0; extra == "dev"
Requires-Dist: virtualenv==20.17.1; extra == "dev"
Requires-Dist: wheel==0.38.4; extra == "dev"
Dynamic: license-file
